coagent/a2a/__init__.py
coagent/a2a/agent.py
coagent/a2a/app.py
coagent/a2a/registry.py
coagent/agents/__init__.py
coagent/agents/aswarm/__init__.py
coagent/agents/aswarm/core.py
coagent/agents/aswarm/repl/__init__.py
coagent/agents/aswarm/repl/repl.py
coagent/agents/aswarm/types.py
coagent/agents/aswarm/util.py
coagent/agents/chat_agent.py
coagent/agents/mcp_agent.py
coagent/agents/mcp_server.py
coagent/agents/memory.py
coagent/agents/messages.py
coagent/agents/model.py
coagent/agents/parallel.py
coagent/agents/react_agent/__init__.py
coagent/agents/react_agent/agent.py
coagent/agents/react_agent/context.py
coagent/agents/react_agent/converter.py
coagent/agents/react_agent/mcp.py
coagent/agents/react_agent/messages.py
coagent/agents/react_agent/model_settings.py
coagent/agents/react_agent/subagent.py
coagent/agents/react_agent/types.py
coagent/agents/react_agent/util.py
coagent/agents/sequential.py
coagent/agents/structured_agent.py
coagent/agents/triage.py
coagent/agents/util.py
coagent/cli/main.py
coagent/core/__init__.py
coagent/core/agent.py
coagent/core/discovery.py
coagent/core/exceptions.py
coagent/core/factory.py
coagent/core/logger.py
coagent/core/messages.py
coagent/core/runtime.py
coagent/core/types.py
coagent/core/util.py
coagent/cos/README.md
coagent/cos/__init__.py
coagent/cos/agent.py
coagent/cos/app.py
coagent/cos/runtime.py
coagent/runtimes/__init__.py
coagent/runtimes/http_runtime.py
coagent/runtimes/local_runtime.py
coagent/runtimes/nats_runtime.py
coagent_python-0.1.2.dist-info/LICENSE
coagent_python-0.1.2.dist-info/METADATA
coagent_python-0.1.2.dist-info/WHEEL
coagent_python-0.1.2.dist-info/entry_points.txt
coagent_python-0.1.2.dist-info/RECORD
